bvc/__init__.py
bvc/checker.py
bvc/configparser.py
bvc/indentation.py
bvc/logger.py
bvc/tests.py
bvc/__pycache__/__init__.cpython-38.pyc
bvc/__pycache__/checker.cpython-38.pyc
bvc/__pycache__/configparser.cpython-38.pyc
bvc/__pycache__/indentation.cpython-38.pyc
bvc/__pycache__/logger.cpython-38.pyc
bvc/__pycache__/tests.cpython-38.pyc
bvc/scripts/__init__.py
bvc/scripts/check_buildout_updates.py
bvc/scripts/find_unused_versions.py
bvc/scripts/indent_buildout.py
bvc/scripts/__pycache__/__init__.cpython-38.pyc
bvc/scripts/__pycache__/check_buildout_updates.cpython-38.pyc
bvc/scripts/__pycache__/find_unused_versions.cpython-38.pyc
bvc/scripts/__pycache__/indent_buildout.cpython-38.pyc
buildout_versions_checker-1.10.0.dist-info/METADATA
buildout_versions_checker-1.10.0.dist-info/WHEEL
buildout_versions_checker-1.10.0.dist-info/entry_points.txt
buildout_versions_checker-1.10.0.dist-info/top_level.txt
buildout_versions_checker-1.10.0.dist-info/RECORD
