Metadata-Version: 2.1
Name: buildout-versions-checker
Version: 1.10.0
Summary: Checks egg updates in your Buildout configurations.
Home-page: https://github.com/Fantomas42/buildout-versions-checker
Author: Fantomas42
Author-email: fantomas42@gmail.com
License: BSD License
Keywords: buildout,versions,updates
Platform: any
Classifier: Framework :: Buildout
Classifier: Intended Audience :: Developers
Classifier: Programming Language :: Python :: 3.7
Classifier: Programming Language :: Python :: 3.8
Classifier: License :: OSI Approved :: BSD License
Classifier: Topic :: Software Development :: Build Tools
Classifier: Topic :: Software Development :: Libraries :: Python Modules
Requires-Dist: packaging
